schemy/__init__.py
schemy/exceptions.py
schemy-0.1.4.dist-info/LICENSE
schemy-0.1.4.dist-info/METADATA
schemy-0.1.4.dist-info/WHEEL
schemy-0.1.4.dist-info/top_level.txt
schemy-0.1.4.dist-info/RECORD
