Metadata-Version: 2.1
Name: schemy
Version: 0.1.4
Summary: Data structure to represent schemas in databases.
Home-page: https://github.com/samuelcorradi/schemy
Author: Samuel Corradi
Author-email: samuelcorradi@gmail.com
Classifier: Programming Language :: Python :: 3
Classifier: License :: OSI Approved :: Apache Software License
Classifier: Operating System :: OS Independent
Classifier: Topic :: Database
Requires-Python: >=3.6.0
License-File: LICENSE
